pargs/Exceptions.py
pargs/Parameter.py
pargs/Parsers.py
pargs/__init__.py
pargs_sfe-0.1.1.dist-info/WHEEL
pargs_sfe-0.1.1.dist-info/entry_points.txt
pargs_sfe-0.1.1.dist-info/METADATA
pargs_sfe-0.1.1.dist-info/RECORD
