Metadata-Version: 2.4
Name: pargs-sfe
Version: 0.1.1
Summary: A small argument parser for dedicated environments with support for env and file based arguments
Author: superfrogemperor
Author-email: superfrogemperor <timo@ney3r.com>
License-Expression: MIT
Classifier: Programming Language :: Python :: 3
Classifier: Operating System :: OS Independent
Requires-Dist: twine>=6.2.0
Requires-Python: >=3.13
Project-URL: Homepage, https://codeberg.org/sfe/pargs
Project-URL: Repository, https://codeberg.org/sfe/pargs
